LICENSE.TXT
MANIFEST.in
README.txt
setup.cfg
setup.py
__dist__/etc/plow/plow.cfg
__dist__/etc/plow/rndaemon.cfg
bin/plow-wrangler
bin/rndaemon
doc/Makefile
doc/__init__.py
doc/__init__.pyc
doc/api.rst
doc/conf.py
doc/conf.pyc
doc/deps.rst
doc/getting_started.rst
doc/index.rst
doc/make.bat
lib/__init__.py
lib/ez_setup.py
plow/__init__.py
plow.egg-info/PKG-INFO
plow.egg-info/SOURCES.txt
plow.egg-info/dependency_links.txt
plow.egg-info/not-zip-safe
plow.egg-info/requires.txt
plow.egg-info/top_level.txt
plow/client/__init__.py
plow/client/conf.py
plow/client/test/__init__.py
plow/client/test/manifest.py
plow/client/test/test_api.py
plow/gui/__init__.py
plow/gui/constants.py
plow/gui/event.py
plow/gui/main.py
plow/gui/manifest.py
plow/gui/util.py
plow/gui/common/__init__.py
plow/gui/common/help.py
plow/gui/common/job.py
plow/gui/common/models.py
plow/gui/common/node.py
plow/gui/common/tree.py
plow/gui/common/widgets.py
plow/gui/form/__init__.py
plow/gui/form/engine.py
plow/gui/form/fwidgets.py
plow/gui/panels/__init__.py
plow/gui/panels/base.py
plow/gui/panels/cluster.py
plow/gui/panels/logs.py
plow/gui/panels/nodes.py
plow/gui/panels/props.py
plow/gui/panels/tasks.py
plow/gui/panels/watch.py
plow/gui/panels/wrangle.py
plow/gui/resources/__init__.py
plow/gui/resources/resources.py
plow/gui/resources/resources.rcc
plow/gui/resources/style.css
plow/rndaemon/__init__.py
plow/rndaemon/client.py
plow/rndaemon/conf.py
plow/rndaemon/core.py
plow/rndaemon/main.py
plow/rndaemon/server.py
plow/rndaemon/utils.py
plow/rndaemon/profile/__init__.py
plow/rndaemon/profile/base.py
plow/rndaemon/profile/libmemstat.dylib
plow/rndaemon/profile/linux.py
plow/rndaemon/profile/macosx.py
plow/rndaemon/profile/posix.py
plow/rndaemon/profile/test.py
plow/rndaemon/rpc/RndNodeApi.py
plow/rndaemon/rpc/RndServiceApi.py
plow/rndaemon/rpc/__init__.py
plow/rndaemon/rpc/constants.py
plow/rndaemon/rpc/ttypes.py
plow/rndaemon/rpc/common/__init__.py
plow/rndaemon/rpc/common/constants.py
plow/rndaemon/rpc/common/ttypes.py
plow/rndaemon/test/__init__.py
plow/rndaemon/test/test_profile.py
plow/rndaemon/test/test_run.py
plow/rndaemon/test/data/cpuinfo.dat
