Metadata-Version: 1.0
Name: plow
Version: 0.4.4
Summary: Python client for the Plow render farm
Home-page: https://github.com/sqlboy/plow/
Author: Matt Chambers & Justin Israel
Author-email: justinisrael@gmail.com
License: UNKNOWN
Keywords: render,renderfarm,management,queue,plow,visualfx,vfx,visual,fx,maya,blender,nuke,3dsmax,houdini
Platform: POSIX / MacOS
Classifier: Development Status :: 3 - Alpha
Classifier: Environment :: Console
Classifier: Operating System :: MacOS :: MacOS X
Classifier: Operating System :: POSIX
Classifier: Operating System :: POSIX :: Linux
Classifier: Operating System :: POSIX :: BSD :: FreeBSD
Classifier: Programming Language :: C++
Classifier: Programming Language :: Python
Classifier: Programming Language :: Python :: 2.6
Classifier: Programming Language :: Python :: 2.7
Classifier: Topic :: System :: Monitoring
Classifier: Topic :: System :: Networking
Classifier: Topic :: System :: Networking :: Monitoring
Classifier: Topic :: Multimedia :: Graphics :: 3D Rendering
Classifier: Topic :: Utilities
Classifier: Topic :: Software Development :: Libraries
Classifier: Topic :: Software Development :: Libraries :: Python Modules
Classifier: Intended Audience :: Developers
Classifier: Intended Audience :: System Administrators
